seed_everything/__init__.py
seed_everything/seeder.py
seed_everything/seeds.py
seed_everything-0.1.0.dist-info/licenses/LICENSE
seed_everything-0.1.0.dist-info/METADATA
seed_everything-0.1.0.dist-info/WHEEL
seed_everything-0.1.0.dist-info/top_level.txt
seed_everything-0.1.0.dist-info/RECORD
